Workbook

Sheet SV Extract_OP Revenue wo Equip
C1: 44957 | F1: 44985 | I1: 45016 | L1: 45046
A2: Freedom_GL | B2: Description | C2: SV | D2: GL | E2: Variance | F2: SV | G2: GL | H2: Variance | I2: SV | J2: GL | K2: Variance | L2: SV | M2: GL | N2: Variance | O2: Comment
A3: 400200 | B3: Connection Fees | C3: 410207.5 | D3: =VLOOKUP($A3,'Gross Margin Details'!$A:$F,3,FALSE) -> 563525.02 | E3: =D3-C3 -> 153317.52 | F3: 374382.5 | G3: =VLOOKUP($A3,'Gross Margin Details'!$A:$F,4,FALSE) -> 549904.93 | H3: =G3-F3 -> 175522.43 | I3: 319992.5 | J3: =VLOOKUP($A3,'Gross Margin Details'!$A:$F,5,FALSE) -> 514040 | K3: =J3-I3 -> 194047.5 | L3: 216425 | M3: =VLOOKUP($A3,'Gross Margin Details'!$A:$F,6,FALSE) -> 517207.74 | N3: =M3-L3 -> 300782.74 | O3: company 197 continuity
A4: 400300 | B4: Monthly Fees | C4: 8205720.5 | D4: =VLOOKUP($A4,'Gross Margin Details'!$A:$F,3,FALSE) -> 8162712.6 | E4: =D4-C4 -> -43007.9 | F4: 8346479.7 | G4: =VLOOKUP($A4,'Gross Margin Details'!$A:$F,4,FALSE) -> 7953849.1 | H4: =G4-F4 -> -392630.64 | I4: 8416769 | J4: =VLOOKUP($A4,'Gross Margin Details'!$A:$F,5,FALSE) -> 8928200.8 | K4: =J4-I4 -> 511431.86 | L4: 8392945.1 | M4: =VLOOKUP($A4,'Gross Margin Details'!$A:$F,6,FALSE) -> 8286992.6 | N4: =M4-L4 -> -105952.54 | O4: deferred revenue
A5: 400303 | B5: Phone Protection Revenue | D5: =VLOOKUP($A5,'Gross Margin Details'!$A:$F,3,FALSE) -> 90799.19 | E5: =D5-C5 -> 90799.19 | G5: =VLOOKUP($A5,'Gross Margin Details'!$A:$F,4,FALSE) -> 83034.68 | H5: =G5-F5 -> 83034.68 | J5: =VLOOKUP($A5,'Gross Margin Details'!$A:$F,5,FALSE) -> 102395.22 | K5: =J5-I5 -> 102395.22 | M5: =VLOOKUP($A5,'Gross Margin Details'!$A:$F,6,FALSE) -> 89667.28 | N5: =M5-L5 -> 89667.28 | O5: Manual JE
A6: 400308 | B6: Above MRC Discounts | C6: -19.96 | D6: =VLOOKUP($A6,'Gross Margin Details'!$A:$F,3,FALSE) -> -19.96 | E6: =D6-C6 -> 0 | G6: =VLOOKUP($A6,'Gross Margin Details'!$A:$F,4,FALSE) -> -2.25 | H6: =G6-F6 -> -2.25 | J6: =VLOOKUP($A6,'Gross Margin Details'!$A:$F,5,FALSE) -> 0 | K6: =J6-I6 -> 0 | M6: =VLOOKUP($A6,'Gross Margin Details'!$A:$F,6,FALSE) -> 0 | N6: =M6-L6 -> 0
A7: 400309 | B7: Credit Monthly Fees | C7: -231679.12 | D7: =VLOOKUP($A7,'Gross Margin Details'!$A:$F,3,FALSE) -> -289795.36 | E7: =D7-C7 -> -58116.24 | F7: -221869.53 | G7: =VLOOKUP($A7,'Gross Margin Details'!$A:$F,4,FALSE) -> -265553.36 | H7: =G7-F7 -> -43683.83 | I7: -178453.4 | J7: =VLOOKUP($A7,'Gross Margin Details'!$A:$F,5,FALSE) -> -216702.86 | K7: =J7-I7 -> -38249.46 | L7: -117316.04 | M7: =VLOOKUP($A7,'Gross Margin Details'!$A:$F,6,FALSE) -> -131889.81 | N7: =M7-L7 -> -14573.77 | O7: deferred revenue
A8: 400399 | B8: Monthly Discount Fees | C8: -124912.62 | D8: =VLOOKUP($A8,'Gross Margin Details'!$A:$F,3,FALSE) -> -120333.21 | E8: =D8-C8 -> 4579.41 | F8: -130823.28 | G8: =VLOOKUP($A8,'Gross Margin Details'!$A:$F,4,FALSE) -> -130259.44 | H8: =G8-F8 -> 563.84 | I8: -119540.49 | J8: =VLOOKUP($A8,'Gross Margin Details'!$A:$F,5,FALSE) -> -118908.75 | K8: =J8-I8 -> 631.74 | L8: -127589.56 | M8: =VLOOKUP($A8,'Gross Margin Details'!$A:$F,6,FALSE) -> -126822.32 | N8: =M8-L8 -> 767.24 | O8: deferred revenue
A9: 401121 | B9: International | C9: 136859.62 | D9: =VLOOKUP($A9,'Gross Margin Details'!$A:$F,3,FALSE) -> 136859.62 | E9: =D9-C9 -> 1.7986167e-08 | F9: 128170.39 | G9: =VLOOKUP($A9,'Gross Margin Details'!$A:$F,4,FALSE) -> 128170.39 | H9: =G9-F9 -> 1.3998942e-08 | I9: 115984.88 | J9: =VLOOKUP($A9,'Gross Margin Details'!$A:$F,5,FALSE) -> 115984.88 | K9: =J9-I9 -> 1.3009412e-08 | L9: 127048.34 | M9: =VLOOKUP($A9,'Gross Margin Details'!$A:$F,6,FALSE) -> 127048.34 | N9: =M9-L9 -> 1.3998942e-08 | O9: deferred revenue
A10: 401171 | B10: National Long Distance | C10: 44194.87 | D10: =VLOOKUP($A10,'Gross Margin Details'!$A:$F,3,FALSE) -> 44171.2 | E10: =D10-C10 -> -23.67 | F10: 44811.06 | G10: =VLOOKUP($A10,'Gross Margin Details'!$A:$F,4,FALSE) -> 42611 | H10: =G10-F10 -> -2200.06 | I10: 45512.29 | J10: =VLOOKUP($A10,'Gross Margin Details'!$A:$F,5,FALSE) -> 47217.93 | K10: =J10-I10 -> 1705.64 | L10: 45719.93 | M10: =VLOOKUP($A10,'Gross Margin Details'!$A:$F,6,FALSE) -> 45043.62 | N10: =M10-L10 -> -676.31 | O10: deferred revenue
A11: 401200 | B11: Mobile Internet | C11: 194215.09 | D11: =VLOOKUP($A11,'Gross Margin Details'!$A:$F,3,FALSE) -> 194076.97 | E11: =D11-C11 -> -138.12 | F11: 196381.35 | G11: =VLOOKUP($A11,'Gross Margin Details'!$A:$F,4,FALSE) -> 186723.74 | H11: =G11-F11 -> -9657.61 | I11: 197724.76 | J11: =VLOOKUP($A11,'Gross Margin Details'!$A:$F,5,FALSE) -> 205886 | K11: =J11-I11 -> 8161.24 | L11: 199786.02 | M11: =VLOOKUP($A11,'Gross Margin Details'!$A:$F,6,FALSE) -> 195941.13 | N11: =M11-L11 -> -3844.89 | O11: deferred revenue
A12: 401400 | B12: VAS | C12: 23676.5 | D12: =VLOOKUP($A12,'Gross Margin Details'!$A:$F,3,FALSE) -> 23671.42 | E12: =D12-C12 -> -5.08 | F12: 24012.7 | G12: =VLOOKUP($A12,'Gross Margin Details'!$A:$F,4,FALSE) -> 22795.42 | H12: =G12-F12 -> -1217.28 | I12: 23814.54 | J12: =VLOOKUP($A12,'Gross Margin Details'!$A:$F,5,FALSE) -> 24982.83 | K12: =J12-I12 -> 1168.29 | L12: 23861.29 | M12: =VLOOKUP($A12,'Gross Margin Details'!$A:$F,6,FALSE) -> 23509.47 | N12: =M12-L12 -> -351.82 | O12: deferred revenue
A13: 401411 | B13: VAS Usage | C13: 12151.11 | D13: =VLOOKUP($A13,'Gross Margin Details'!$A:$F,3,FALSE) -> 12151.11 | E13: =D13-C13 -> -3.0013325e-10 | F13: 12017.08 | G13: =VLOOKUP($A13,'Gross Margin Details'!$A:$F,4,FALSE) -> 12017.08 | H13: =G13-F13 -> -3.0013325e-10 | I13: 11652.78 | J13: =VLOOKUP($A13,'Gross Margin Details'!$A:$F,5,FALSE) -> 11652.78 | K13: =J13-I13 -> -3.0013325e-10 | L13: 11163.06 | M13: =VLOOKUP($A13,'Gross Margin Details'!$A:$F,6,FALSE) -> 11163.06 | N13: =M13-L13 -> 0 | O13: deferred revenue
A14: 404000 | B14: International Roaming | C14: 92456.5 | D14: =VLOOKUP($A14,'Gross Margin Details'!$A:$F,3,FALSE) -> 92456.5 | E14: =D14-C14 -> 0 | F14: 80962.5 | G14: =VLOOKUP($A14,'Gross Margin Details'!$A:$F,4,FALSE) -> 80962.5 | H14: =G14-F14 -> 0 | I14: 74776.5 | J14: =VLOOKUP($A14,'Gross Margin Details'!$A:$F,5,FALSE) -> 74776.5 | K14: =J14-I14 -> 0 | L14: 83696.5 | M14: =VLOOKUP($A14,'Gross Margin Details'!$A:$F,6,FALSE) -> 83696.5 | N14: =M14-L14 -> 0 | O14: deferred revenue
A15: 404200 | B15: Mobile Internet Intl Roaming | C15: 563102.97 | D15: =VLOOKUP($A15,'Gross Margin Details'!$A:$F,3,FALSE) -> 553203.91 | E15: =D15-C15 -> -9899.06 | F15: 535153.06 | G15: =VLOOKUP($A15,'Gross Margin Details'!$A:$F,4,FALSE) -> 504865.15 | H15: =G15-F15 -> -30287.91 | I15: 553322.49 | J15: =VLOOKUP($A15,'Gross Margin Details'!$A:$F,5,FALSE) -> 557860.79 | K15: =J15-I15 -> 4538.3 | L15: 658601.23 | M15: =VLOOKUP($A15,'Gross Margin Details'!$A:$F,6,FALSE) -> 653211.2 | N15: =M15-L15 -> -5390.03 | O15: deferred revenue
A16: 404500 | B16: Domestic Roaming | C16: 5718.77 | D16: =VLOOKUP($A16,'Gross Margin Details'!$A:$F,3,FALSE) -> 5718.77 | E16: =D16-C16 -> 5.0022209e-11 | F16: 4798.74 | G16: =VLOOKUP($A16,'Gross Margin Details'!$A:$F,4,FALSE) -> 4798.74 | H16: =G16-F16 -> -1.0004442e-11 | I16: 3814.52 | J16: =VLOOKUP($A16,'Gross Margin Details'!$A:$F,5,FALSE) -> 3814.52 | K16: =J16-I16 -> -3.0013325e-11 | L16: 4321.03 | M16: =VLOOKUP($A16,'Gross Margin Details'!$A:$F,6,FALSE) -> 4321.03 | N16: =M16-L16 -> -3.0013325e-11 | O16: deferred revenue
A17: 404510 | B17: SMS International Roaming | C17: 28566 | D17: =VLOOKUP($A17,'Gross Margin Details'!$A:$F,3,FALSE) -> 28566 | E17: =D17-C17 -> 0 | F17: 20806.5 | G17: =VLOOKUP($A17,'Gross Margin Details'!$A:$F,4,FALSE) -> 20806.5 | H17: =G17-F17 -> 0 | I17: 22468.5 | J17: =VLOOKUP($A17,'Gross Margin Details'!$A:$F,5,FALSE) -> 22468.5 | K17: =J17-I17 -> 0 | L17: 29712.5 | M17: =VLOOKUP($A17,'Gross Margin Details'!$A:$F,6,FALSE) -> 29712.5 | N17: =M17-L17 -> 0 | O17: deferred revenue
A18: 405210 | B18: Mobile Internet Domestic Roaming | C18: 320817.29 | D18: =VLOOKUP($A18,'Gross Margin Details'!$A:$F,3,FALSE) -> 320164.72 | E18: =D18-C18 -> -652.57 | F18: 343575.82 | G18: =VLOOKUP($A18,'Gross Margin Details'!$A:$F,4,FALSE) -> 316483.13 | H18: =G18-F18 -> -27092.69 | I18: 313131.7 | J18: =VLOOKUP($A18,'Gross Margin Details'!$A:$F,5,FALSE) -> 343114.58 | K18: =J18-I18 -> 29982.88 | L18: 362748.56 | M18: =VLOOKUP($A18,'Gross Margin Details'!$A:$F,6,FALSE) -> 335574.21 | N18: =M18-L18 -> -27174.35 | O18: deferred revenue
... A21: 406001 | B21: Extended Warranty Commissions Revenue | C21: 166188.78 | D21: =VLOOKUP($A21,'Gross Margin Details'!$A:$F,3,FALSE) -> 0 | E21: =D21-C21 -> -166188.78 | F21: 166033.34 | G21: =VLOOKUP($A21,'Gross Margin Details'!$A:$F,4,FALSE) -> 0 | H21: =G21-F21 -> -166033.34 | I21: 167528.47 | J21: =VLOOKUP($A21,'Gross Margin Details'!$A:$F,5,FALSE) -> 0 | K21: =J21-I21 -> -167528.47 | L21: 165537.1 | M21: =VLOOKUP($A21,'Gross Margin Details'!$A:$F,6,FALSE) -> 0 | N21: =M21-L21 -> -165537.1 | O21: Manual JE
A22: 406003 | B22: Apple Care | D22: =VLOOKUP($A22,'Gross Margin Details'!$A:$F,3,FALSE) -> 122 | E22: =D22-C22 -> 122 | G22: =VLOOKUP($A22,'Gross Margin Details'!$A:$F,4,FALSE) -> 2566 | H22: =G22-F22 -> 2566 | J22: =VLOOKUP($A22,'Gross Margin Details'!$A:$F,5,FALSE) -> 4042 | K22: =J22-I22 -> 4042 | M22: =VLOOKUP($A22,'Gross Margin Details'!$A:$F,6,FALSE) -> -479 | N22: =M22-L22 -> -479 | O22: Manual JE
A23: 406010 | B23: 911 Levy Revenue | C23: -84173.8 | D23: =VLOOKUP($A23,'Gross Margin Details'!$A:$F,3,FALSE) -> -67664.37 | E23: =D23-C23 -> 16509.43 | F23: -83613.3 | G23: =VLOOKUP($A23,'Gross Margin Details'!$A:$F,4,FALSE) -> -67038.21 | H23: =G23-F23 -> 16575.09 | I23: -83211.45 | J23: =VLOOKUP($A23,'Gross Margin Details'!$A:$F,5,FALSE) -> -66509.45 | K23: =J23-I23 -> 16702 | L23: -82547.4 | M23: =VLOOKUP($A23,'Gross Margin Details'!$A:$F,6,FALSE) -> -65733.96 | N23: =M23-L23 -> 16813.44 | O23: Manual JE
A24: Subtotal | C24: =SUM(C3:C23) -> 9777244.7 | D24: =SUM(D3:D23) -> 9744350.2 | E24: =SUM(E3:E23) -> -32894.55 | F24: =SUM(F3:F23) -> 9854851.2 | G24: =SUM(G3:G23) -> 9458540.2 | H24: =SUM(H3:H23) -> -396310.99 | I24: =SUM(I3:I23) -> 9899354.3 | J24: =SUM(J3:J23) -> 10566584 | ... N24: =SUM(N3:N23) -> 83646.63
C25: =C24-[1]Summary!$AK$54 -> 0 | D25: =D24-'Gross Margin Details'!C127 -> 0 | F25: =F24-[1]Summary!$Y$54 -> 0 | G25: =G24-'Gross Margin Details'!D127 -> 0 | I25: =I24-[1]Summary!$N$54 -> 0 | J25: =J24-'Gross Margin Details'!E127 -> 0 | L25: =L24-[1]Summary!$C$54 -> 0 | M25: =M24-'Gross Margin Details'!F127 -> 0

Sheet Gross Margin Details
B1: Last Refresh: 5/5/2023 9:44:15 AM
B2: Shaw Finance
B3: WLS01 Financials
B4: W1 Wireless Brand - Shaw Mobile
B5: #Versions: Reporting - Current Forecast
A6: Freedom_GL | C6: =CHOOSE(2, "5449260031", "Jan 23") -> Jan 23 | D6: =CHOOSE(2, "5449570028", "Feb 23") -> Feb 23 | E6: =CHOOSE(2, "5449850031", "Mar 23") -> Mar 23 | F6: =CHOOSE(2, "5450160030", "Apr 23") -> Apr 23
B7: =CHOOSE(2, "415000000058", "Wireless Revenue & Variable Cost Details") -> Wireless Revenue & Variable Cost Details
B8: =CHOOSE(2, "415000000147", "Service Revenue Details") -> Service Revenue Details
A9: 400300 | B9: =CHOOSE(2, "415000000060", "Postpaid - Base Plan MRC - Phone") -> Postpaid - Base Plan MRC - Phone | C9: 8162712.6 | D9: 7953849.1 | E9: 8928200.8 | F9: 8286992.6
B10: =CHOOSE(2, "415000000061", "Postpaid - Base Plan MRC - Tablets") -> Postpaid - Base Plan MRC - Tablets | C10: 0 | D10: 0 | E10: 0 | F10: 0
A11: 400309 | B11: =CHOOSE(2, "415000000062", "Postpaid - MRC Discounts") -> Postpaid - MRC Discounts | C11: -289795.36 | D11: -265553.36 | E11: -216702.86 | F11: -131889.81
A12: 401171 | B12: =CHOOSE(2, "415000000063", "Postpaid - Add on - LD - Domestic - Voice") -> Postpaid - Add on - LD - Domestic - Voice | C12: 44171.2 | D12: 42611 | E12: 47217.93 | F12: 45043.62
B13: =CHOOSE(2, "415000000064", "Postpaid - Add on - LD - International - Voice") -> Postpaid - Add on - LD - International - Voice | C13: 0 | D13: 0 | E13: 0 | F13: 0
A14: 401200 | B14: =CHOOSE(2, "415000000065", "Postpaid - Add on - Data - Domestic - MB") -> Postpaid - Add on - Data - Domestic - MB | C14: 194076.97 | D14: 186723.74 | E14: 205886 | F14: 195941.13
A15: 401400 | B15: =CHOOSE(2, "415000000066", "Postpaid - Add on - VAS - Domestic - VAS") -> Postpaid - Add on - VAS - Domestic - VAS | C15: 23671.42 | D15: 22795.42 | E15: 24982.83 | F15: 23509.47
B16: =CHOOSE(2, "415000000067", "Postpaid - Add on - VAS - Domestic - SMS") -> Postpaid - Add on - VAS - Domestic - SMS | C16: 0 | D16: 0 | E16: 0 | F16: 0
B17: =CHOOSE(2, "415000000068", "Postpaid - Overage - LD - Domestic - Voice - Local") -> Postpaid - Overage - LD - Domestic - Voice - Local | C17: 0 | D17: 0 | E17: 0 | F17: 0
B18: =CHOOSE(2, "415000000069", "Postpaid - Overage - LD - Domestic - Voice - National LD") -> Postpaid - Overage - LD - Domestic - Voice - National LD | C18: 0 | D18: 0 | E18: 0 | F18: 0
A19: 401121 | B19: =CHOOSE(2, "415000000070", "Postpaid - Overage - LD - International - Voice - Intl.") -> Postpaid - Overage - LD - International - Voice - Intl. | C19: 136859.62 | D19: 128170.39 | E19: 115984.88 | F19: 127048.34
B20: =CHOOSE(2, "415000000071", "Postpaid - Overage - Data - Domestic - MB") -> Postpaid - Overage - Data - Domestic - MB | C20: 0 | D20: 0 | E20: 0 | F20: 0
A21: 401411 | B21: =CHOOSE(2, "415000000072", "Postpaid - Overage - VAS - Domestic - VAS") -> Postpaid - Overage - VAS - Domestic - VAS | C21: 12151.11 | D21: 12017.08 | E21: 11652.78 | F21: 11163.06
B22: =CHOOSE(2, "415000000073", "Postpaid - Overage - VAS - Domestic - SMS") -> Postpaid - Overage - VAS - Domestic - SMS | C22: 0 | D22: 0 | E22: 0 | F22: 0
B23: =CHOOSE(2, "415000000074", "Postpaid - Overage - VAS - International - SMS") -> Postpaid - Overage - VAS - International - SMS | C23: 0 | D23: 0 | E23: 0 | F23: 0
A24: 404000 | B24: =CHOOSE(2, "415000000075", "Postpaid - Overage - Roaming - International Roaming - Voice") -> Postpaid - Overage - Roaming - International Roaming - Voice | C24: 92456.5 | D24: 80962.5 | E24: 74776.5 | F24: 83696.5
A25: 404200 | B25: =CHOOSE(2, "415000000076", "Postpaid - Overage - Roaming - International Roaming - MB") -> Postpaid - Overage - Roaming - International Roaming - MB | C25: 553203.91 | D25: 504865.15 | E25: 557860.79 | F25: 653211.2
A26: 404510 | B26: =CHOOSE(2, "415000000077", "Postpaid - Overage - Roaming - International Roaming - SMS") -> Postpaid - Overage - Roaming - International Roaming - SMS | C26: 28566 | D26: 20806.5 | E26: 22468.5 | F26: 29712.5
A27: 404500 | B27: =CHOOSE(2, "415000000078", "Postpaid - Overage - Roaming - Domestic Roaming - Voice") -> Postpaid - Overage - Roaming - Domestic Roaming - Voice | C27: 5718.77 | D27: 4798.74 | E27: 3814.52 | F27: 4321.03
A28: 405210 | B28: =CHOOSE(2, "415000000079", "Postpaid - Overage - Roaming - Domestic Roaming - MB") -> Postpaid - Overage - Roaming - Domestic Roaming - MB | C28: 320164.72 | D28: 316483.13 | E28: 343114.58 | F28: 335574.21
A29: 405500 | B29: =CHOOSE(2, "415000000080", "Postpaid - Overage - Roaming - Domestic Roaming - SMS") -> Postpaid - Overage - Roaming - Domestic Roaming - SMS | C29: 223.25 | D29: 223.5 | E29: 154.75 | F29: 162.2
B30: =CHOOSE(2, "415000000081", "Postpaid - Overage - Tablets - Data - Domestic - MB") -> Postpaid - Overage - Tablets - Data - Domestic - MB | C30: 0 | D30: 0 | E30: 0 | F30: 0
A31: 400200 | B31: =CHOOSE(2, "415000000082", "Postpaid - Other - Connection Fees") -> Postpaid - Other - Connection Fees | C31: 563525.02 | D31: 549904.93 | E31: 514040 | F31: 517207.74
A32: 400303 | B32: =CHOOSE(2, "415000000083", "Postpaid - Other - Phone Protection") -> Postpaid - Other - Phone Protection | C32: 90799.19 | D32: 83034.68 | E32: 102395.22 | F32: 89667.28
A33: 400308 | B33: =CHOOSE(2, "415000000084", "Postpaid - Credit & Adjustment - Above MRC Disc.") -> Postpaid - Credit & Adjustment - Above MRC Disc. | C33: -19.96 | D33: -2.25 | E33: 0 | F33: 0
A34: 400399 | B34: =CHOOSE(2, "415000000085", "Postpaid - Credit & Adjustment - Cust. Service Adj.") -> Postpaid - Credit & Adjustment - Cust. Service Adj. | C34: -120333.21 | D34: -130259.44 | E34: -118908.75 | F34: -126822.32
B35: =CHOOSE(2, "415000000086", "Postpaid - Disc. Amort. Allocated to/from Wireline") -> Postpaid - Disc. Amort. Allocated to/from Wireline | C35: 5065778.4 | D35: 5062325.4 | E35: 5059109.8 | F35: 5046943.8
B36: =CHOOSE(2, "415000000087", "Postpaid - Disc. Amort. Allocated to/from HS") -> Postpaid - Disc. Amort. Allocated to/from HS | C36: 221207.7 | D36: 216357.84 | E36: 219428.06 | F36: 222446.49
B37: =CHOOSE(2, "415000000059", "Service Revenue - Postpaid") -> Service Revenue - Postpaid | C37: 15105138 | D37: 14790114 | E37: 15895476 | F37: 15413929
B38: =CHOOSE(2, "415000000115", "Visitor Roaming") -> Visitor Roaming | C38: 0 | D38: 0 | E38: 0 | F38: 0
B39: =CHOOSE(2, "415000000116", "Service Revenue - Total") -> Service Revenue - Total | C39: 15105138 | D39: 14790114 | E39: 15895476 | F39: 15413929
B40: =CHOOSE(2, "415000000148", "Equipment Revenue Details") -> Equipment Revenue Details
B41: =CHOOSE(2, "415000000144", "Handset Revenue") -> Handset Revenue | C41: 3049859.1 | D41: 3453078.2 | E41: 2152666 | F41: -749570.42
B42: =CHOOSE(2, "415000000240", "TradeUp BRV Revenue Reduction") -> TradeUp BRV Revenue Reduction | C42: 0 | D42: 0 | E42: 0 | F42: 0
B43: =CHOOSE(2, "415000000143", "Handset Revenue - Consignment") -> Handset Revenue - Consignment | C43: 56459 | D43: 65254 | E43: 69191 | F43: 7068
B44: =CHOOSE(2, "415000000142", "Handset Revenue - Connection Fee Equip") -> Handset Revenue - Connection Fee Equip | C44: 0 | D44: 0 | E44: 0 | F44: 0
B45: =CHOOSE(2, "415000000141", "Handset Revenue - Tab Discount") -> Handset Revenue - Tab Discount | C45: -640365.08 | D45: -569947.86 | E45: -458635.02 | F45: -65632.43
B46: =CHOOSE(2, "415000000140", "Handset Revenue - Tab Subsidy Dealer") -> Handset Revenue - Tab Subsidy Dealer | C46: 0 | D46: 0 | E46: 0 | F46: 0
B47: =CHOOSE(2, "415000000139", "Tab Cancellation Charges") -> Tab Cancellation Charges | C47: 38323.69 | D47: 11116.14 | E47: 48165.17 | F47: 29123.64
B48: =CHOOSE(2, "415000000138", "Other (Trade In Value Credit)") -> Other (Trade In Value Credit) | C48: 23025.41 | D48: 7545.67 | E48: 6458.42 | F48: 1429.97
B49: =CHOOSE(2, "415000000137", "Dealer / NR Margin") -> Dealer / NR Margin | C49: 20908.69 | D49: -66314.81 | E49: 703.47 | F49: 90322.52
B50: =CHOOSE(2, "415000000136", "Dealer / NR Margin - Dealer") -> Dealer / NR Margin - Dealer | C50: 0 | D50: 0 | E50: 0 | F50: 0
B51: =CHOOSE(2, "415000000135", "Handset Return Allowance") -> Handset Return Allowance | C51: -22605.43 | D51: -20008.67 | E51: 34988.04 | F51: 6282.18
B52: =CHOOSE(2, "415000000134", "Handset Price Protection") -> Handset Price Protection | C52: 73066 | D52: 10728.24 | E52: -240 | F52: 360
B53: =CHOOSE(2, "415000000133", "TAB Bad Debt") -> TAB Bad Debt | C53: 0 | D53: 0 | E53: 0 | F53: 0
B54: =CHOOSE(2, "415000000132", "Accessories Revenue") -> Accessories Revenue | C54: 115062.14 | D54: 26970.08 | E54: 94563.83 | F54: 30337.59
B55: =CHOOSE(2, "415000000131", "Disc. Amort. Allocated to/from Wireline") -> Disc. Amort. Allocated to/from Wireline | C55: -324328.85 | D55: -242813.72 | E55: -194466.86 | F55: -113388.52
B56: =CHOOSE(2, "415000000130", "Equipment Revenue - Total") -> Equipment Revenue - Total | C56: 2389404.7 | D56: 2675607.2 | E56: 1753394 | F56: -763667.47
B57: =CHOOSE(2, "415000000149", "Other Revenue Details") -> Other Revenue Details
A58: 406000 | B58: =CHOOSE(2, "415000000129", "Postpaid Late Pymt / Bill Pymt fee - Dealer") -> Postpaid Late Pymt / Bill Pymt fee - Dealer | C58: -6259.18 | D58: 11581.6 | E58: 12113.06 | F58: 11873.22
B59: =CHOOSE(2, "415000000128", "Prepaid Late Pymt / Bill Pymt fee - Dealer") -> Prepaid Late Pymt / Bill Pymt fee - Dealer | C59: 0 | D59: 0 | E59: 0 | F59: 0
B60: =CHOOSE(2, "415000000127", "Bill Payment Fee - CS") -> Bill Payment Fee - CS | C60: 19400 | D60: 1900 | E60: 2000 | F60: 600
B61: =CHOOSE(2, "415000000126", "Device Extended Warranty Commission") -> Device Extended Warranty Commission | C61: 0 | D61: 0 | E61: 0 | F61: 0
A62: 406003 | B62: =CHOOSE(2, "415000000125", "Apple Care") -> Apple Care | C62: 122 | D62: 2566 | E62: 4042 | F62: -479
B63: =CHOOSE(2, "415000000124", "Drop Ship Commission Rev") -> Drop Ship Commission Rev | C63: 0 | D63: 0 | E63: 0 | F63: 0
B64: =CHOOSE(2, "415000000123", "A2P Revenue") -> A2P Revenue | C64: 0 | D64: 0 | E64: 0 | F64: 0
B65: =CHOOSE(2, "415000000242", "Subscriptions") -> Subscriptions | C65: 0 | D65: 0 | E65: 0 | F65: 0
A66: 406010 | B66: =CHOOSE(2, "415000000122", "911 Levy Revenue") -> 911 Levy Revenue | C66: -67664.37 | D66: -67038.21 | E66: -66509.45 | F66: -65733.96
B67: =CHOOSE(2, "415000000121", "FAST Dial Revenue") -> FAST Dial Revenue | C67: 0 | D67: 0 | E67: 0 | F67: 0
A68: 406080 | B68: =CHOOSE(2, "415000000120", "Trade-in Commissions Revenue") -> Trade-in Commissions Revenue | C68: 7157.52 | D68: 1509.14 | E68: 1291.68 | F68: 333.39
B69: =CHOOSE(2, "415000000119", "Loaner Rent Revenue") -> Loaner Rent Revenue | C69: 0 | D69: 0 | E69: 0 | F69: 0
B70: =CHOOSE(2, "415000000118", "Other Revenue - Total") -> Other Revenue - Total | C70: -47244.03 | D70: -49481.47 | E70: -47062.71 | F70: -53406.35
B71: =CHOOSE(2, "415000000150", "Service Cost Details") -> Service Cost Details
B72: =CHOOSE(2, "415000000151", "Domestic Roaming - Fixed Cost") -> Domestic Roaming - Fixed Cost | C72: -12350.37 | D72: -12868.39 | E72: -12816.53 | F72: -12539.76
B73: =CHOOSE(2, "415000000152", "Domestic Roaming - Voice") -> Domestic Roaming - Voice | C73: -90497.01 | D73: -81093.19 | E73: -94332.01 | F73: -92359.97
B74: =CHOOSE(2, "415000000153", "Domestic Roaming - SMS") -> Domestic Roaming - SMS | C74: -10454.59 | D74: -9851.04 | E74: -11133.6 | F74: -11195.43
B75: =CHOOSE(2, "415000000154", "Domestic Roaming - Data") -> Domestic Roaming - Data | C75: -654604.24 | D75: -616192.44 | E75: -706096.2 | F75: -684759.28
B76: =CHOOSE(2, "415000000155", "International Roaming - US - Voice") -> International Roaming - US - Voice | C76: 1330.74 | D76: -3286.54 | E76: 97211.24 | F76: -395.79
B77: =CHOOSE(2, "415000000156", "International Roaming - US - SMS") -> International Roaming - US - SMS | C77: 348.09 | D77: -272.25 | E77: -466.76 | F77: -398
B78: =CHOOSE(2, "415000000157", "International Roaming - US - Data") -> International Roaming - US - Data | C78: -62996.74 | D78: -69769.16 | E78: -83490.48 | F78: -72997.2
B79: =CHOOSE(2, "415000000158", "International Roaming - Fixed Cost") -> International Roaming - Fixed Cost | C79: -12101.03 | D79: -13371.27 | E79: -15435.56 | F79: -13572.37
B80: =CHOOSE(2, "415000000159", "International Roaming - Voice") -> International Roaming - Voice | C80: -28134.75 | D80: -19443.93 | E80: -19857.99 | F80: -14303.68
B81: =CHOOSE(2, "415000000160", "International Roaming - SMS") -> International Roaming - SMS | C81: -2546.37 | D81: -1932.04 | E81: -1820.09 | F81: -1515.16
B82: =CHOOSE(2, "415000000161", "International Roaming - Data") -> International Roaming - Data | C82: -22244.11 | D82: -18313.82 | E82: -21916.78 | F82: -16585.12
B83: =CHOOSE(2, "415000000162", "Domestic LD") -> Domestic LD | C83: -5924.36 | D83: -3907.14 | E83: -6674.09 | F83: -5658.74
B84: =CHOOSE(2, "415000000163", "Other International LD") -> Other International LD | C84: -3693.45 | D84: -7262.58 | E84: -3272.45 | F84: -2806.18
B85: =CHOOSE(2, "415000000164", "US LD") -> US LD | C85: 0 | D85: 0 | E85: 0 | F85: 0
B86: =CHOOSE(2, "415000000165", "Traffic Imbalance") -> Traffic Imbalance | C86: 0 | D86: 0 | E86: 0 | F86: 0
B87: =CHOOSE(2, "415000000166", "SMS Cost") -> SMS Cost | C87: -38770.04 | D87: -52364.41 | E87: -27463.35 | F87: -26301.31
B88: =CHOOSE(2, "415000000167", "Fixed Interconnect (Leased Lines)") -> Fixed Interconnect (Leased Lines) | C88: -54381.43 | D88: -55969.31 | E88: -58280.36 | F88: -56551.3
B89: =CHOOSE(2, "415000000168", "Interconnect Setup Fees (911)") -> Interconnect Setup Fees (911) | C89: -82584.21 | D89: -84796.97 | E89: -82757.43 | F89: -84632.62
B90: =CHOOSE(2, "415000000169", "Content & VAS") -> Content & VAS | C90: -3797.13 | D90: -3684.98 | E90: -4379.77 | F90: -3747.48
B91: =CHOOSE(2, "415000000170", "Blackberry Subscription") -> Blackberry Subscription | C91: 0 | D91: 0 | E91: 0 | F91: 0
B92: =CHOOSE(2, "415000000171", "Contribution Fees") -> Contribution Fees | C92: 0 | D92: 0 | E92: 0 | F92: 0
B93: =CHOOSE(2, "415000000172", "Other - Revenue Sharing") -> Other - Revenue Sharing | C93: 0 | D93: 0 | E93: 0 | F93: 0
B94: =CHOOSE(2, "415000000173", "Other - Costs for Mobile Number") -> Other - Costs for Mobile Number | C94: 0 | D94: 0 | E94: 0 | F94: 0
B95: =CHOOSE(2, "415000000174", "Service Cost - Total") -> Service Cost - Total | C95: -1083401 | D95: -1054379.5 | E95: -1052982.2 | F95: -1100319.4
B96: =CHOOSE(2, "415000000202", "Equipment Cost Details") -> Equipment Cost Details
B97: =CHOOSE(2, "415000000241", "TradeUp BRV Cost Reduction") -> TradeUp BRV Cost Reduction | C97: 0 | D97: 0 | E97: 0 | F97: 0
B98: =CHOOSE(2, "415000000201", "Handsets Sold - Dealer New") -> Handsets Sold - Dealer New | C98: 215991.05 | D98: -805956.37 | E98: 86876.35 | F98: 1125640.1
B99: =CHOOSE(2, "415000000200", "Handsets Sold - Dealer Margin New") -> Handsets Sold - Dealer Margin New | C99: 0 | D99: 0 | E99: 0 | F99: 0
B100: =CHOOSE(2, "415000000199", "Handsets Sold - Dealer Used") -> Handsets Sold - Dealer Used | C100: 0 | D100: 0 | E100: 0 | F100: 0
...
